bigcode_tokenizer/__init__.py
bigcode_tokenizer/cli.py
bigcode_tokenizer/parallel_tokenizer.py
bigcode_tokenizer/token.py
bigcode_tokenizer/tokenizer.py
bigcode_tokenizer-0.1.0.data/scripts/bigcode-tokenizer
bigcode_tokenizer-0.1.0.dist-info/DESCRIPTION.rst
bigcode_tokenizer-0.1.0.dist-info/METADATA
bigcode_tokenizer-0.1.0.dist-info/RECORD
bigcode_tokenizer-0.1.0.dist-info/WHEEL
bigcode_tokenizer-0.1.0.dist-info/metadata.json
bigcode_tokenizer-0.1.0.dist-info/top_level.txt
tests/__init__.py
tests/java_tokenizer_test.py
tests/token_test.py
